MANIFEST.in
setup.py
RenewablesAutomate.egg-info/PKG-INFO
RenewablesAutomate.egg-info/SOURCES.txt
RenewablesAutomate.egg-info/dependency_links.txt
RenewablesAutomate.egg-info/requires.txt
RenewablesAutomate.egg-info/top_level.txt
pyarmor_runtime_000000/__init__.py
pyarmor_runtime_000000/pyarmor_runtime
pyarmor_runtime_000000/pyarmor_runtime.pyd
pyarmor_runtime_000000/__pycache__/__init__.cpython-311.pyc