Metadata-Version: 2.1
Name: RenewablesAutomate
Version: 1.0.7
Summary: Renewable Energy Monitoring Management Interface
Author: dpocarroll
Author-email: dpocarroll@outlook.com
Classifier: Programming Language :: Python :: 3
Classifier: License :: OSI Approved :: MIT License
Classifier: Operating System :: Microsoft :: Windows 
Requires-Python: >=3.6
